pynano/__init__.py
pynano/base.py
pynano/day.py
pynano/region.py
pynano/site.py
pynano/user.py
pynano-0.1.1.dist-info/DESCRIPTION.rst
pynano-0.1.1.dist-info/METADATA
pynano-0.1.1.dist-info/RECORD
pynano-0.1.1.dist-info/WHEEL
pynano-0.1.1.dist-info/metadata.json
pynano-0.1.1.dist-info/top_level.txt
