Metadata-Version: 2.0
Name: pynano
Version: 0.1.1
Summary: A simple Python library for the NaNoWriMo API
Home-page: https://pynano.readthedocs.org/
Author: Travis Veazey
Author-email: travisvz@gmail.com
License: MIT
Keywords: nanowrimo wordcount api
Platform: UNKNOWN
Classifier: Development Status :: 4 - Beta
Classifier: Intended Audience :: Developers
Classifier: License :: OSI Approved :: MIT License
Classifier: Programming Language :: Python :: 2
Classifier: Programming Language :: Python :: 2.7
Classifier: Programming Language :: Python :: 3
Classifier: Programming Language :: Python :: 3.2
Classifier: Programming Language :: Python :: 3.3
Classifier: Programming Language :: Python :: 3.4
Classifier: Programming Language :: Python :: 3.5
Classifier: Topic :: Software Development :: Libraries
Classifier: Topic :: Software Development :: Libraries :: Python Modules
Requires-Dist: requests (>=2.9.1)
Requires-Dist: xmltodict (>=0.9.2)
